HW2/1-ALU/2_Behavior/alu.v
//Behavior ¡Vlevel (event-driven) 
module alu(
    ctrl,
    x,
    y,
    carry,
    out 
);
    
    input  [3:0] ctrl;
    input  [7:0] x;
    input  [7:0] y;
    output       carry;
    output reg [7:0] out;
    reg carry;
    reg carry_add,carry_sub;

always@(*) begin
    case(ctrl)
        4'b0000: {carry,out}={x+y};
        4'b0001: {carry,out}={x-y};
        4'b0010: {carry,out}={1'b0,x&y};
        4'b0011: {carry,out}={1'b0,x|y};
        4'b0100: {carry,out}={1'b0,~x};
        4'b0101: {carry,out}={1'b0,x^y};
        4'b0110: {carry,out}={1'b0,~(x|y)};
        4'b0111: {carry,out}={1'b0,y<<x[2:0]};
        4'b1000: {carry,out}={1'b0,y>>x[2:0]};
        4'b1001: {carry,out}={1'b0,x[7],x[7:1]};
        4'b1010: {carry,out}={1'b0,x[6:0],x[7]};
        4'b1011: {carry,out}={1'b0,x[0],x[7:1]};
        4'b1100: {carry,out}={1'b0,(x==y)?1:0};
        4'b1101: {carry,out}=0;
        4'b1110: {carry,out}=0;
        4'b1111: {carry,out}=0;
    endcase
end
endmodule

HW2/1-ALU/2_Behavior/tb.v
`timescale 1ns/10ps
`define CYCLE  10
`define HCYCLE  5
`define INFILE "Bin.pattern"
`define OUTFILE "Bout_golden.pattern" 

module alu_rtl_tb;

    reg  [3:0] ctrl;
    reg  [7:0] x;
    reg  [7:0] y;
    wire       carry;
    wire [7:0] out;

    reg clk;

    integer i;
    
    alu alu1(
        ctrl     ,
        x        ,
        y        ,
        carry    ,
        out  
    );
	always begin #(`CYCLE * 0.5) clk = ~clk;
        end
    initial begin
        // initialization
        clk = 1'b0;
        i=0;

        //add
        #(`CYCLE*0.2)
        ctrl=4'd0;
        x=8'd3;
        y=8'd10;
        #(`CYCLE*0.4)
        if (out != 8'd13 || carry != 1'b0) $display( "error on (%d)", i );
        i=i+1;
        #(`CYCLE*0.4)

        #(`CYCLE*0.2)
        ctrl=4'd0;
        x=8'b11111111;
        y=8'b00000001;
        #(`CYCLE*0.4)
        if (out != 8'd0 || carry != 1'b0) $display( "error on (%b)", carry );
        i=i+1;
        #(`CYCLE*0.4)

        #(`CYCLE*0.2)
        ctrl=4'd0;
        x=8'b01111111;
        y=8'b01111111;
        #(`CYCLE*0.4)
        if (out != 8'b11111110 || carry != 1'b0) $display( "error on (%d)", i );
        i=i+1;
        #(`CYCLE*0.4)

        //sub
        #(`CYCLE*0.2)
        ctrl=4'd1;
        x=8'd14;
        y=8'd7;
        #(`CYCLE*0.4)
        if (out != 8'd7 || carry != 1'b0) $display( "error on (%d)", i );
        i=i+1;
        #(`CYCLE*0.4)

        //and
        #(`CYCLE*0.2)
        ctrl=4'd2;
        x=8'b11110011;
        y=8'b00001001;
        #(`CYCLE*0.4)
        if (out != 8'b00000001 || carry != 1'b0) $display( "error on (%d)", i );
        i=i+1;
        #(`CYCLE*0.4)

        //Shift left logical variable
        #(`CYCLE*0.2)
        ctrl=4'd7;
        y=8'b11110011;
        x=8'b11110011;
        #(`CYCLE*0.4)
        if (out != 8'b10011000 || carry != 1'b0) $display( "error on (%d)", i );
        i=i+1;
        #(`CYCLE*0.4)

        //Shift right logical variable
        #(`CYCLE*0.2)
        ctrl=4'd8;
        y=8'b10110011;
        x=8'b00000100;
        #(`CYCLE*0.4)
        if (out != 8'b00001011 || carry != 1'b0) $display( "error on (%b)", out );
        i=i+1;
        #(`CYCLE*0.4)

        //Shift right arithmetic
        #(`CYCLE*0.2)
        ctrl=4'd9;
        x=8'b10110011;
        y=8'b00000000;
        #(`CYCLE*0.4)
        if (out != 8'b11011001 || carry != 1'b0) $display( "error on (%d)", i );
        i=i+1;
        #(`CYCLE*0.4)

        //Shift left rotate
        #(`CYCLE*0.2)
        ctrl=4'd10;
        x=8'b10110011;
        y=8'b11111111;
        #(`CYCLE*0.4)
        if (out != 8'b01100111 || carry != 1'b0) $display( "error on (%d)", i );
        i=i+1;
        #(`CYCLE*0.4)

        //equal
        #(`CYCLE*0.2)
        ctrl=4'd12;
        x=8'b10110011;
        y=8'b10110011;
        #(`CYCLE*0.4)
        if (out != 8'b00000001 || carry != 1'b0) $display( "error on (%d)", i );
        i=i+1;
        #(`CYCLE*0.4)

        //equal
        #(`CYCLE*0.2)
        ctrl=4'd12;
        x=8'b10110011;
        y=8'b10100011;
        #(`CYCLE*0.4)
        if (out != 8'b00000000 || carry != 1'b0) $display( "error on (%d)", i );
        i=i+1;
        #(`CYCLE*0.4)

        //nop
        #(`CYCLE*0.2)
        ctrl=4'd14;
        x=8'b10110011;
        y=8'b10101111;
        #(`CYCLE*0.4)
        if (out != 8'b00000000 || carry != 1'b0) $display( "error on (%d)", i );
        i=i+1;
        #(`CYCLE*0.4)
        $finish;
	end
	
endmodule

HW2/1-ALU/2_Behavior/alu.vcd
$date
    Apr 12, 2018  16:31:37
$end
$version
    TOOL:	ncsim	10.20-s114
$end
$timescale
    10 ps
$end

$scope module alu_rtl_tb $end
$var reg       4 !    ctrl [3:0] $end
$var reg       8 "    x [7:0] $end
$var reg       8 #    y [7:0] $end
$var wire      1 $    carry  $end
$var wire      8 %    out [7:0] $end
$var reg       1 &    clk  $end
$var integer  32 '    i  $end

$scope module alu1 $end
$var wire      4 (    ctrl [3:0] $end
$var wire      8 )    x [7:0] $end
$var wire      8 *    y [7:0] $end
$var reg       1 +    carry  $end
$var reg       8 ,    out [7:0] $end
$var reg       1 -    carry_add  $end
$var reg       1 .    carry_sub  $end
$upscope $end

$upscope $end

$enddefinitions $end
$dumpvars
bx !
bx "
bx #
x$
bx %
0&
b0 '
bx (
bx )
bx *
x+
bx ,
x-
x.
$end
#200
b0 !
b11 "
b1010 #
b1010 *
b11 )
b0 (
b1101 ,
0+
0$
b1101 %
#500
1&
#600
b1 '
#1000
0&
#1200
b11111111 "
b1 #
b1 *
b11111111 )
b0 ,
b0 %
#1500
1&
#1600
b10 '
#2000
0&
#2200
b1111111 "
b1111111 #
b1111111 *
b1111111 )
b11111110 ,
b11111110 %
#2500
1&
#2600
b11 '
#3000
0&
#3200
b1 !
b1110 "
b111 #
b111 *
b1110 )
b1 (
b111 ,
b111 %
#3500
1&
#3600
b100 '
#4000
0&
#4200
b10 !
b11110011 "
b1001 #
b1001 *
b11110011 )
b10 (
b1 ,
b1 %
#4500
1&
#4600
b101 '
#5000
0&
#5200
b111 !
b11110011 #
b11110011 *
b111 (
b10011000 ,
b10011000 %
#5500
1&
#5600
b110 '
#6000
0&
#6200
b1000 !
b10110011 #
b100 "
b100 )
b10110011 *
b1000 (
b1011 ,
b1011 %
#6500
1&
#6600
b111 '
#7000
0&
#7200
b1001 !
b10110011 "
b0 #
b0 *
b10110011 )
b1001 (
b11011001 ,
b11011001 %
#7500
1&
#7600
b1000 '
#8000
0&
#8200
b1010 !
b11111111 #
b11111111 *
b1010 (
b1100111 ,
b1100111 %
#8500
1&
#8600
b1001 '
#9000
0&
#9200
b1100 !
b10110011 #
b10110011 *
b1100 (
b1 ,
b1 %
#9500
1&
#9600
b1010 '
#10000
0&
#10200
b10100011 #
b10100011 *
b0 ,
b0 %
#10500
1&
#10600
b1011 '
#11000
0&
#11200
b1110 !
b10101111 #
b10101111 *
b1110 (
#11500
1&
#11600
b1100 '
