HW2/2-RegisterFile/register_file.v
module register_file(
    Clk  ,
    WEN  ,
    RW   ,
    busW ,
    RX   ,
    RY   ,
    busX ,
    busY
);
input        Clk, WEN;
input  [2:0] RW, RX, RY;
input  [7:0] busW;
output [7:0] busX, busY;
    
// write your design here
reg [7:0] r0_w, r1_w, r2_w, r3_w, r4_w, r5_w, r6_w, r7_w;
reg [7:0] r0_r, r1_r, r2_r, r3_r, r4_r, r5_r, r6_r, r7_r;

    
always@(*) begin
	if(WEN==1'b1)
	begin
		case(RW)
			3'b000: r0_w=busW;
			3'b001: r1_w=busW;
			3'b010: r2_w=busW;
			3'b011: r3_w=busW;
			3'b100: r4_w=busW;
			3'b101: r5_w=busW;
			3'b110: r6_w=busW;
			3'b111: r7_w=busW;
		endcase
	end
	case(RX)
		3'b000: busX=r0_r;
		3'b001: busX=r1_r;
		3'b010: busX=r2_r;
		3'b011: busX=r3_r;
		3'b100: busX=r4_r;
		3'b101: busX=r5_r;
		3'b110: busX=r6_r;
		3'b111: busX=r7_r
   	endcase
	case(RY)
		3'b000: busY=r0_r;
		3'b001: busY=r1_r;
		3'b010: busY=r2_r;
		3'b011: busY=r3_r;
		3'b100: busY=r4_r;
		3'b101: busY=r5_r;
		3'b110: busY=r6_r;
		3'b111: busY=r7_r;
	endcase
end

always@(posedge Clk) begin
	r0_r<=8'b00000000;
	r1_r<=r1_w;
	r2_r<=r2_w;
	r3_r<=r3_w;
	r4_r<=r4_w;
	r5_r<=r5_w;
	r6_r<=r6_w;
	r7_r<=r7_w;
end	

endmodule

HW2/2-RegisterFile/tb.v
`timescale 1ns/10ps
`define CYCLE  10
`define HCYCLE  5

module simple_calculator_tb;
    // port declaration for design-under-test
    reg Clk, WEN;
    reg  [2:0] RW, RX, RY;
    reg  [7:0] busW;
    wire [7:0] busX, busY;

    reg  stop;
 
    // instantiate the design-under-test
    register_file rf(
        Clk  ,
        WEN[0]  ,
        RW[2:0]   ,
        busW ,
        RX[2:0]   ,
        RY[2:0]   ,
        busX[7:0] ,
        busY[7:0]
    );
    // waveform dump
//    initial begin
//        $fsdbDumpfile("simple_calc.fsdb");
//        $fsdbDumpvars;
//    end
    
    // clock generation
    always#(`HCYCLE) Clk = ~Clk;
    
    integer err_count;
    initial begin
        // initialization
        Clk = 1'b0;
        
        #(`CYCLE*0.2)
        $display( "store 10101010 in REG#1");
        $display( "0:00000000");        
        $display( "1:10101010");        
        $display( "2:xxxxxxxx");     
        $display( "3:xxxxxxxx");     
        $display( "4:xxxxxxxx");     
        $display( "5:xxxxxxxx");     
        $display( "6:xxxxxxxx");     
        $display( "7:xxxxxxxx");     
        WEN = 1'b1; RW=3'd1; busW = 1'b10101010; RX = 3'd0; RY = 3'd0;
        #(`CYCLE*0.4)
        RX = 3'd0;
        $display("0X %b", busX );   
        RX = 3'd1;
        $display("1X %b", busX );   
        RX = 3'd2;
        $display("2X %b", busX );        
        RX = 3'd3;
        $display("3X %b", busX );        
        RX = 3'd4;
        $display("4X %b", busX );        
        RX = 3'd5;
        $display("5X %b", busX );        
        RX = 3'd6;
        $display("6X %b", busX ); 
        RX = 3'd7;
        $display("7X %b", busX ); 
        RY = 3'd0;
        $display("0Y %b", busY );   
        RY = 3'd1;
        $display("1Y %b", busY );   
        RY = 3'd2;
        $display("2Y %b", busY );        
        RY = 3'd3;
        $display("3Y %b", busY );        
        RY = 3'd4;
        $display("4Y %b", busY );        
        RY = 3'd5;
        $display("5Y %b", busY );        
        RY = 3'd6;
        $display("6Y %b", busY ); 
        RY = 3'd7;
        $display("7Y %b", busY ); 
        #(`CYCLE*0.4)

        #(`CYCLE*0.2)
        $display( "store 11111111 in REG#8");
        $display( "0:00000000");        
        $display( "1:10101010");        
        $display( "2:xxxxxxxx");     
        $display( "3:xxxxxxxx");     
        $display( "4:xxxxxxxx");     
        $display( "5:xxxxxxxx");     
        $display( "6:xxxxxxxx");     
        $display( "7:11111111");     
        WEN = 1'b1; RW=3'd8; busW = 1'b11111111; RX = 3'd0; RY = 3'd0;
        #(`CYCLE*0.4)
        RX = 3'd0;
        $display("0X %b", busX );   
        RX = 3'd1;
        $display("1X %b", busX );   
        RX = 3'd2;
        $display("2X %b", busX );        
        RX = 3'd3;
        $display("3X %b", busX );        
        RX = 3'd4;
        $display("4X %b", busX );        
        RX = 3'd5;
        $display("5X %b", busX );        
        RX = 3'd6;
        $display("6X %b", busX ); 
        RX = 3'd7;
        $display("7X %b", busX ); 
        RY = 3'd0;
        $display("0Y %b", busY );   
        RY = 3'd1;
        $display("1Y %b", busY );   
        RY = 3'd2;
        $display("2Y %b", busY );        
        RY = 3'd3;
        $display("3Y %b", busY );        
        RY = 3'd4;
        $display("4Y %b", busY );        
        RY = 3'd5;
        $display("5Y %b", busY );        
        RY = 3'd6;
        $display("6Y %b", busY ); 
        RY = 3'd7;
        $display("7Y %b", busY ); 
        #(`CYCLE*0.4)

        #(`CYCLE*0.2)
        $display( "store 11001100 in REG#0");
        $display( "0:00000000");        
        $display( "1:10101010");        
        $display( "2:xxxxxxxx");     
        $display( "3:xxxxxxxx");     
        $display( "4:xxxxxxxx");     
        $display( "5:xxxxxxxx");     
        $display( "6:xxxxxxxx");     
        $display( "7:11111111");     
        WEN = 1'b1; RW=3'd0; busW =  1'b11001100; RX = 3'd0; RY = 3'd0;
        #(`CYCLE*0.4)
        RX = 3'd0;
        $display("0X %b", busX );   
        RX = 3'd1;
        $display("1X %b", busX );   
        RX = 3'd2;
        $display("2X %b", busX );        
        RX = 3'd3;
        $display("3X %b", busX );        
        RX = 3'd4;
        $display("4X %b", busX );        
        RX = 3'd5;
        $display("5X %b", busX );        
        RX = 3'd6;
        $display("6X %b", busX ); 
        RX = 3'd7;
        $display("7X %b", busX ); 
        RY = 3'd0;
        $display("0Y %b", busY );   
        RY = 3'd1;
        $display("1Y %b", busY );   
        RY = 3'd2;
        $display("2Y %b", busY );        
        RY = 3'd3;
        $display("3Y %b", busY );        
        RY = 3'd4;
        $display("4Y %b", busY );        
        RY = 3'd5;
        $display("5Y %b", busY );        
        RY = 3'd6;
        $display("6Y %b", busY ); 
        RY = 3'd7;
        $display("7Y %b", busY ); 
        #(`CYCLE*0.4)

        #(`CYCLE*0.2)
        $display( "false store 11001100 in REG#3");
        $display( "0:00000000");        
        $display( "1:10101010");        
        $display( "2:xxxxxxxx");     
        $display( "3:xxxxxxxx");     
        $display( "4:xxxxxxxx");     
        $display( "5:xxxxxxxx");     
        $display( "6:xxxxxxxx");     
        $display( "7:11111111");     
        WEN = 1'b0; RW=3'd3; busW = 1'b11001100; RX = 3'd0; RY = 3'd0;
        #(`CYCLE*0.4)
        RX = 3'd0;
        $display("0X %b", busX );   
        RX = 3'd1;
        $display("1X %b", busX );   
        RX = 3'd2;
        $display("2X %b", busX );        
        RX = 3'd3;
        $display("3X %b", busX );        
        RX = 3'd4;
        $display("4X %b", busX );        
        RX = 3'd5;
        $display("5X %b", busX );        
        RX = 3'd6;
        $display("6X %b", busX ); 
        RX = 3'd7;
        $display("7X %b", busX ); 
        RY = 3'd0;
        $display("0Y %b", busY );   
        RY = 3'd1;
        $display("1Y %b", busY );   
        RY = 3'd2;
        $display("2Y %b", busY );        
        RY = 3'd3;
        $display("3Y %b", busY );        
        RY = 3'd4;
        $display("4Y %b", busY );        
        RY = 3'd5;
        $display("5Y %b", busY );        
        RY = 3'd6;
        $display("6Y %b", busY ); 
        RY = 3'd7;
        $display("7Y %b", busY ); 
        #(`CYCLE*0.4)

        $display("Use your eyes to debug. Ha ha !");
    end
endmodule

HW2/2-RegisterFile/register_file.vcd
$date
    Apr  6, 2018  16:51:49
$end
$version
    TOOL:	ncsim	10.20-s114
$end
$timescale
    10 ps
$end

$scope module simple_calculator_tb $end
$var reg       1 !    Clk  $end
$var reg       1 "    WEN  $end
$var reg       3 #    RW [2:0] $end
$var reg       3 $    RX [2:0] $end
$var reg       3 %    RY [2:0] $end
$var reg       8 &    busW [7:0] $end
$var wire      8 '    busX [7:0] $end
$var wire      8 (    busY [7:0] $end
$var reg       1 )    stop  $end
$var integer  32 *    err_count  $end

$scope module rf $end
$var wire      1 +    Clk  $end
$var wire      1 ,    WEN  $end
$var wire      3 -    RW [2:0] $end
$var wire      3 .    RX [2:0] $end
$var wire      3 /    RY [2:0] $end
$var wire      8 0    busW [7:0] $end
$var reg       8 1    busX [7:0] $end
$var reg       8 2    busY [7:0] $end
$var reg       8 3    r0_w [7:0] $end
$var reg       8 4    r1_w [7:0] $end
$var reg       8 5    r2_w [7:0] $end
$var reg       8 6    r3_w [7:0] $end
$var reg       8 7    r4_w [7:0] $end
$var reg       8 8    r5_w [7:0] $end
$var reg       8 9    r6_w [7:0] $end
$var reg       8 :    r7_w [7:0] $end
$var reg       8 ;    r0_r [7:0] $end
$var reg       8 <    r1_r [7:0] $end
$var reg       8 =    r2_r [7:0] $end
$var reg       8 >    r3_r [7:0] $end
$var reg       8 ?    r4_r [7:0] $end
$var reg       8 @    r5_r [7:0] $end
$var reg       8 A    r6_r [7:0] $end
$var reg       8 B    r7_r [7:0] $end
$upscope $end

$upscope $end

$enddefinitions $end
$dumpvars
0!
x"
bx #
bx $
bx %
bx &
bx '
bx (
x)
bx *
0+
x,
bx -
bx .
bx /
bx 0
bx 1
bx 2
bx 3
bx 4
bx 5
bx 6
bx 7
bx 8
bx 9
bx :
bx ;
bx <
bx =
bx >
bx ?
bx @
bx A
bx B
$end
#200
1"
b1 #
b10101010 &
b0 $
b0 %
b0 /
b0 .
b1 -
b10101010 0
1,
b10101010 4
#500
1!
1+
b0 ;
b10101010 <
b0 1
b0 2
b0 (
b0 '
#600
b1 $
b10 $
b11 $
b100 $
b101 $
b110 $
b111 $
b1 %
b10 %
b11 %
b100 %
b101 %
b110 %
b111 %
b111 /
b111 .
bx 1
bx 2
bx (
bx '
#1000
0!
0+
#1200
b111 #
b11111111 &
b0 $
b0 %
b0 /
b0 .
b111 -
b11111111 0
b11111111 :
b0 1
b0 2
b0 (
b0 '
#1500
1!
1+
b11111111 B
#1600
b1 $
b10 $
b11 $
b100 $
b101 $
b110 $
b111 $
b1 %
b10 %
b11 %
b100 %
b101 %
b110 %
b111 %
b111 /
b111 .
b11111111 1
b11111111 2
b11111111 (
b11111111 '
#2000
0!
0+
#2200
b0 #
b11001100 &
b0 $
b0 %
b0 /
b0 .
b0 -
b11001100 0
b11001100 3
b0 1
b0 2
b0 (
b0 '
#2500
1!
1+
#2600
b1 $
b10 $
b11 $
b100 $
b101 $
b110 $
b111 $
b1 %
b10 %
b11 %
b100 %
b101 %
b110 %
b111 %
b111 /
b111 .
b11111111 1
b11111111 2
b11111111 (
b11111111 '
#3000
0!
0+
#3200
0"
b11 #
b0 $
b0 %
b0 /
b0 .
b11 -
0,
b0 1
b0 2
b0 (
b0 '
#3500
1!
1+
#3600
b1 $
b10 $
b11 $
b100 $
b101 $
b110 $
b111 $
b1 %
b10 %
b11 %
b100 %
b101 %
b110 %
b111 %
b111 /
b111 .
b11111111 1
b11111111 2
b11111111 (
b11111111 '
