2HW/DSD_HW2_b04901067 2/3-SimpleCalculator/alu.v
//Behavior ¡Vlevel (event-driven) 
module alu(
    ctrl,
    x,
    y,
    carry,
    out 
);
    
    input  [3:0] ctrl;
    input  [7:0] x;
    input  [7:0] y;
    output       carry;
    output reg [7:0] out;
    reg carry;
    reg carry_add,carry_sub;

always@(*) begin
    case(ctrl)
        4'b0000: {carry,out}={{x[7],x[7:0]}+{y[7],y[6:0]}};
        4'b0001: {carry,out}={{x[7],x[7:0]}-{y[7],y[6:0]}};
        4'b0010: {carry,out}={1'b0,x&y};
        4'b0011: {carry,out}={1'b0,x|y};
        4'b0100: {carry,out}={1'b0,~x};
        4'b0101: {carry,out}={1'b0,x^y};
        4'b0110: {carry,out}={1'b0,~(x|y)};
        4'b0111: {carry,out}={1'b0,y<<x[2:0]};
        4'b1000: {carry,out}={1'b0,y>>x[2:0]};
        4'b1001: {carry,out}={1'b0,x[7],x[7:1]};
        4'b1010: {carry,out}={1'b0,x[6:0],x[7]};
        4'b1011: {carry,out}={1'b0,x[0],x[7:1]};
        4'b1100: {carry,out}={1'b0,(x==y)?1:0};
        4'b1101: {carry,out}=0;
        4'b1110: {carry,out}=0;
        4'b1111: {carry,out}=0;
    endcase
end
endmodule

HW2/2-RegisterFile/register_file.v
module register_file(
    Clk  ,
    WEN  ,
    RW   ,
    busW ,
    RX   ,
    RY   ,
    busX ,
    busY
);
input        Clk, WEN;
input  [2:0] RW, RX, RY;
input  [7:0] busW;
output [7:0] busX, busY;
    
// write your design here
reg [7:0] r0_w, r1_w, r2_w, r3_w, r4_w, r5_w, r6_w, r7_w;
reg [7:0] r0_r, r1_r, r2_r, r3_r, r4_r, r5_r, r6_r, r7_r;

    
always@(*) begin
	if(WEN==1'b1)
	begin
		case(RW)
			3'b000: r0_w=busW;
			3'b001: r1_w=busW;
			3'b010: r2_w=busW;
			3'b011: r3_w=busW;
			3'b100: r4_w=busW;
			3'b101: r5_w=busW;
			3'b110: r6_w=busW;
			3'b111: r7_w=busW;
		endcase
	end
	case(RX)
		3'b000: busX=r0_r;
		3'b001: busX=r1_r;
		3'b010: busX=r2_r;
		3'b011: busX=r3_r;
		3'b100: busX=r4_r;
		3'b101: busX=r5_r;
		3'b110: busX=r6_r;
		3'b111: busX=r7_r
   	endcase
	case(RY)
		3'b000: busY=r0_r;
		3'b001: busY=r1_r;
		3'b010: busY=r2_r;
		3'b011: busY=r3_r;
		3'b100: busY=r4_r;
		3'b101: busY=r5_r;
		3'b110: busY=r6_r;
		3'b111: busY=r7_r;
	endcase
end

always@(posedge Clk) begin
	r0_r<=8'b00000000;
	r1_r<=r1_w;
	r2_r<=r2_w;
	r3_r<=r3_w;
	r4_r<=r4_w;
	r5_r<=r5_w;
	r6_r<=r6_w;
	r7_r<=r7_w;
end	

endmodule

HW2/3-SimpleCalculator/simple_calculator.v
module simple_calculator(
    Clk,
    WEN,
    RW,
    RX,
    RY,
    DataIn,
    Sel,
    Ctrl,
    busY,
    Carry
);

    input        Clk;
    input        WEN;
    input  [2:0] RW, RX, RY;
    input  [7:0] DataIn;
    input        Sel;
    input  [3:0] Ctrl;
    output [7:0] busY;
    output       Carry;
    reg   [7:0] x;
    reg   [7:0] y;
    wire  [7:0] busX, out;

register_file r(
    Clk  ,
    WEN  ,
    RW   ,
    out  ,
    RX   ,
    RY   ,
    busX ,
    busY
    );

    alu a(
    Ctrl,
    x,
    y,
    carry,
    out
    );

// declaration of wire/reg
always@(*) begin

    if (Sel==1)
        x=busX;
    else
        x=DataIn;
    y=busY;
    
end
    
// submodule instantiation

endmodule

HW2/3-SimpleCalculator/simple_calculator_tb.v
`timescale 1ns/10ps
`define CYCLE  10
`define HCYCLE  5

module simple_calculator_tb;
    // port declaration for design-under-test
    reg        Clk;
    reg        WEN;
    reg  [2:0] RW, RX, RY;
    reg  [7:0] DataIn;
    reg        Sel;
    reg  [3:0] Ctrl;
    wire [7:0] busY;
    wire       Carry;
 
    // instantiate the design-under-test
    simple_calculator u_calc(
        .Clk    (Clk),
        .WEN    (WEN),
        .RW     (RW),
        .RX     (RX),
        .RY     (RY),
        .DataIn (DataIn),
        .Sel    (Sel),
        .Ctrl   (Ctrl),
        .busY   (busY),
        .Carry  (Carry)
    );

    // waveform dump
//    initial begin
//        $fsdbDumpfile("simple_calc.fsdb");
//        $fsdbDumpvars;
//    end
    
    // clock generation
    always#(`HCYCLE) Clk = ~Clk;
    
    // test pattern
    parameter A = {4'd0,4'd13};
    parameter B = {4'd0,4'd12};
    parameter maskB0 = {8{B[0]}};
    parameter maskB1 = {8{B[1]}};
    parameter maskB2 = {8{B[2]}};
    parameter maskB3 = {8{B[3]}};
    parameter sum0 = A*B[0];
    parameter sum1 = A*B[1:0];
    parameter sum2 = A*B[2:0];
    parameter C = A*B;
    
    // simulation
    integer err_count;
    initial begin
        // initialization
        Clk = 1'b1;
        err_count = 0;
        
        // 4-bit x 4-bit unsigned multiplication
        $display( "4-bit x 4-bit unsigned multiplication" );
        
        #(`CYCLE*0.2)
        $display( "1: store multiplicand A=%2d in REG#1", A );
        $display( "    [REG#1 = add %b REG#0]", A );        
        WEN = 1'b1; RW = 3'd1; RX = 3'd0; RY = 3'd0;
        Ctrl = 4'b0000; Sel = 1'b0; DataIn = A;
        #(`CYCLE*0.8)
        #(`CYCLE*0.2)
        WEN = 1'b0; RW = 3'd1; RX = 3'd0; RY = 3'd1;
        Ctrl = 4'b0011; Sel = 1'b0; DataIn = 8'd0;
        #(`CYCLE*0.3)
        if( busY==A ) $display( "    .... passed." );
        else begin 
            err_count = err_count+1;
            $display( "    .... failed, design(%b) != expected(%b)", busY, A );
        end
        #(`HCYCLE)
        
        #(`CYCLE*0.2)
        $display( "2: store multiplier B=%2d in REG#2", B );
        $display( "    [REG#2 = add %b REG#0]", B ); 
        WEN = 1'b1; RW = 3'd2; RX = 3'd0; RY = 3'd0;
        Ctrl = 4'b0000; Sel = 1'b0; DataIn = B;
        #(`CYCLE*0.8)
        #(`CYCLE*0.2)
        WEN = 1'b0; RW = 3'd1; RX = 3'd0; RY = 3'd2;
        Ctrl = 4'b0011; Sel = 1'b0; DataIn = 8'd0;
        #(`CYCLE*0.3)
        if( busY==B ) $display( "    .... passed." );
        else begin 
            err_count = err_count+1;
            $display( "    .... failed, design(%b) != expected(%b)", busY, B );
        end
        #(`HCYCLE)        
        
        #(`CYCLE*0.2)
        $display( "3: set REG#3 = (B[0]==1)? 8'b11111111: 8'b00000000" );
        $display( "    [REG#3 = and 0000_0001 REG#2]" ); 
        WEN = 1'b1; RW = 3'd3; RX = 3'd0; RY = 3'd2;
        Ctrl = 4'b0010; Sel = 1'b0; DataIn = 8'd1;
        #(`CYCLE*0.8)
        #(`CYCLE*0.2)
        $display( "    [REG#3 = sub REG#0 REG#3]" ); 
        WEN = 1'b1; RW = 3'd3; RX = 3'd0; RY = 3'd3;
        Ctrl = 4'b0001; Sel = 1'b1; DataIn = 8'd0;
        #(`CYCLE*0.8)
        #(`CYCLE*0.2)
        WEN = 1'b0; RW = 3'd3; RX = 3'd0; RY = 3'd3;
        Ctrl = 4'b0011; Sel = 1'b1; DataIn = 8'd0;
        #(`CYCLE*0.3)
        if( busY==maskB0 ) $display( "    .... passed." );
        else begin
            err_count = err_count+1;
            $display( "    .... failed, design(%b) != expected(%b)", busY, maskB0 );
        end
        #(`HCYCLE)         

        #(`CYCLE*0.2)
        $display( "4: set REG#4 = (B[1]==1)? 8'b11111111: 8'b00000000" );
        $display( "    [REG#2 = sra REG#2]" ); 
        WEN = 1'b1; RW = 3'd2; RX = 3'd2; RY = 3'd2;
        Ctrl = 4'b1001; Sel = 1'b1; DataIn = 8'd0;
        #(`CYCLE*0.8)
        #(`CYCLE*0.2)
        $display( "    [REG#4 = and 0000_0001 REG#2]" ); 
        WEN = 1'b1; RW = 3'd4; RX = 3'd0; RY = 3'd2;
        Ctrl = 4'b0010; Sel = 1'b0; DataIn = 8'd1;
        #(`CYCLE*0.8)
        #(`CYCLE*0.2)
        $display( "    [REG#4 = sub REG#0 REG#4]" ); 
        WEN = 1'b1; RW = 3'd4; RX = 3'd0; RY = 3'd4;
        Ctrl = 4'b0001; Sel = 1'b1; DataIn = 8'd0;
        #(`CYCLE*0.8)
        #(`CYCLE*0.2)
        WEN = 1'b0; RW = 3'd4; RX = 3'd0; RY = 3'd4;
        Ctrl = 4'b0011; Sel = 1'b1; DataIn = 8'd0;
        #(`CYCLE*0.3)
        if( busY==maskB1 ) $display( "    .... passed." );
        else begin 
            err_count = err_count+1;
            $display( "    .... failed, design(%b) != expected(%b)", busY, maskB1 );
        end
        #(`HCYCLE)  

        #(`CYCLE*0.2)
        $display( "5: set REG#5 = (B[2]==1)? 8'b11111111: 8'b00000000" );
        $display( "    [REG#2 = sra REG#2]" ); 
        WEN = 1'b1; RW = 3'd2; RX = 3'd2; RY = 3'd2;
        Ctrl = 4'b1001; Sel = 1'b1; DataIn = 8'd0;
        #(`CYCLE*0.8)
        #(`CYCLE*0.2)
        $display( "    [REG#5 = and 0000_0001 REG#2]" ); 
        WEN = 1'b1; RW = 3'd5; RX = 3'd0; RY = 3'd2;
        Ctrl = 4'b0010; Sel = 1'b0; DataIn = 8'd1;
        #(`CYCLE*0.8)
        #(`CYCLE*0.2)
        $display( "    [REG#5 = sub REG#0 REG#5]" ); 
        WEN = 1'b1; RW = 3'd5; RX = 3'd0; RY = 3'd5;
        Ctrl = 4'b0001; Sel = 1'b1; DataIn = 8'd0;
        #(`CYCLE*0.8)
        #(`CYCLE*0.2)
        WEN = 1'b0; RW = 3'd5; RX = 3'd0; RY = 3'd5;
        Ctrl = 4'b0011; Sel = 1'b1; DataIn = 8'd0;
        #(`CYCLE*0.3)
        if( busY==maskB2 ) $display( "    .... passed." );
        else begin 
            err_count = err_count+1;
            $display( "    .... failed, design(%b) != expected(%b)", busY, maskB2 );
        end
        #(`HCYCLE) 
    
        #(`CYCLE*0.2)
        $display( "6: set REG#6 = (B[3]==1)? 8'b11111111: 8'b00000000" );
        $display( "    [REG#2 = sra REG#2]" ); 
        WEN = 1'b1; RW = 3'd2; RX = 3'd2; RY = 3'd2;
        Ctrl = 4'b1001; Sel = 1'b1; DataIn = 8'd0;
        #(`CYCLE*0.8)
        #(`CYCLE*0.2)
        $display( "    [REG#6 = and 0000_0001 REG#2]" ); 
        WEN = 1'b1; RW = 3'd6; RX = 3'd0; RY = 3'd2;
        Ctrl = 4'b0010; Sel = 1'b0; DataIn = 8'd1;
        #(`CYCLE*0.8)
        #(`CYCLE*0.2)
        $display( "    [REG#6 = sub REG#0 REG#6]" ); 
        WEN = 1'b1; RW = 3'd6; RX = 3'd0; RY = 3'd6;
        Ctrl = 4'b0001; Sel = 1'b1; DataIn = 8'd0;
        #(`CYCLE*0.8)
        #(`CYCLE*0.2)
        WEN = 1'b0; RW = 3'd6; RX = 3'd0; RY = 3'd6;
        Ctrl = 4'b0011; Sel = 1'b1; DataIn = 8'd0;
        #(`CYCLE*0.3)
        if( busY==maskB3 ) $display( "    .... passed." );
        else begin
            err_count = err_count+1;
            $display( "    .... failed, design(%b) != expected(%b)", busY, maskB3 );
        end
        #(`HCYCLE) 
        
        $display( "7: shift & summation, REG#7 = A*B[0]" );
        #(`CYCLE*0.2)
        $display( "    [REG#3 = and REG#1 REG#3]" ); 
        WEN = 1'b1; RW = 3'd3; RX = 3'd1; RY = 3'd3;
        Ctrl = 4'b0010; Sel = 1'b1; DataIn = 8'd0;
        #(`CYCLE*0.8)
        #(`CYCLE*0.2)
        $display( "    [REG#7 = add REG#0 REG#3]" ); 
        WEN = 1'b1; RW = 3'd7; RX = 3'd0; RY = 3'd3;
        Ctrl = 4'b0000; Sel = 1'b1; DataIn = 8'd0;
        #(`CYCLE*0.8)
        #(`CYCLE*0.2)
        WEN = 1'b0; RW = 3'd7; RX = 3'd0; RY = 3'd7;
        Ctrl = 4'b0011; Sel = 1'b1; DataIn = 8'd0;
        #(`CYCLE*0.3)
        if( busY==sum0 ) $display( "    .... passed." );
        else begin
            err_count = err_count+1;
            $display( "    .... failed, design(%b) != expected(%b)", busY, sum0 );
        end
        #(`HCYCLE)
        
        $display( "8: shift & summation, REG#7 = A*B[1:0]" );
        #(`CYCLE*0.2)
        $display( "    [REG#4 = and REG#1 REG#4]" );
        WEN = 1'b1; RW = 3'd4; RX = 3'd1; RY = 3'd4;
        Ctrl = 4'b0010; Sel = 1'b1; DataIn = 8'd0;
        #(`CYCLE*0.8)
        #(`CYCLE*0.2)
        $display( "    [REG#4 = sll 0000_0001 REG#4]" );
        WEN = 1'b1; RW = 3'd4; RX = 3'd0; RY = 3'd4;
        Ctrl = 4'b0111; Sel = 1'b0; DataIn = 8'd1;
        #(`CYCLE*0.8)
        #(`CYCLE*0.2)
        $display( "    [REG#7 = add REG#7 REG#4]" ); 
        WEN = 1'b1; RW = 3'd7; RX = 3'd7; RY = 3'd4;
        Ctrl = 4'b0000; Sel = 1'b1; DataIn = 8'd0;
        #(`CYCLE*0.8)
        #(`CYCLE*0.2)
        WEN = 1'b0; RW = 3'd7; RX = 3'd0; RY = 3'd7;
        Ctrl = 4'b0011; Sel = 1'b1; DataIn = 8'd0;
        #(`CYCLE*0.3)
        if( busY==sum1 ) $display( "    .... passed." );
        else begin     
            err_count = err_count+1;
            $display( "    .... failed, design(%b) != expected(%b)", busY, sum1 );
        end
        #(`HCYCLE)
        
        $display( "9: shift & summation, REG#7 = A*B[2:0]" );
        #(`CYCLE*0.2)
        $display( "    [REG#5 = and REG#1 REG#5]" );
        WEN = 1'b1; RW = 3'd5; RX = 3'd1; RY = 3'd5;
        Ctrl = 4'b0010; Sel = 1'b1; DataIn = 8'd0;
        #(`CYCLE*0.8)
        #(`CYCLE*0.2)
        $display( "    [REG#5 = sll 0000_0010 REG#5]" );
        WEN = 1'b1; RW = 3'd5; RX = 3'd0; RY = 3'd5;
        Ctrl = 4'b0111; Sel = 1'b0; DataIn = 8'd2;
        #(`CYCLE*0.8)
        #(`CYCLE*0.2)
        $display( "    [REG#7 = add REG#7 REG#5]" ); 
        WEN = 1'b1; RW = 3'd7; RX = 3'd7; RY = 3'd5;
        Ctrl = 4'b0000; Sel = 1'b1; DataIn = 8'd0;
        #(`CYCLE*0.8)
        #(`CYCLE*0.2)
        WEN = 1'b0; RW = 3'd7; RX = 3'd0; RY = 3'd7;
        Ctrl = 4'b0011; Sel = 1'b1; DataIn = 8'd0;
        #(`CYCLE*0.3)
        if( busY==sum2 ) $display( "    .... passed." );
        else begin 
            err_count = err_count+1;
            $display( "    .... failed, design(%b) != expected(%b)", busY, sum2 );
        end
        #(`HCYCLE)
        
        $display( "10:shift & summation, REG#7 = A*B" );
        #(`CYCLE*0.2)
        $display( "    [REG#6 = and REG#1 REG#6]" );
        WEN = 1'b1; RW = 3'd6; RX = 3'd1; RY = 3'd6;
        Ctrl = 4'b0010; Sel = 1'b1; DataIn = 8'd0;
        #(`CYCLE*0.8)
        #(`CYCLE*0.2)
        $display( "    [REG#6 = sll 0000_0011 REG#6]" );
        WEN = 1'b1; RW = 3'd6; RX = 3'd0; RY = 3'd6;
        Ctrl = 4'b0111; Sel = 1'b0; DataIn = 8'd3;
        #(`CYCLE*0.8)
        #(`CYCLE*0.2)
        $display( "    [REG#7 = add REG#7 REG#6]" ); 
        WEN = 1'b1; RW = 3'd7; RX = 3'd7; RY = 3'd6;
        Ctrl = 4'b0000; Sel = 1'b1; DataIn = 8'd0;
        #(`CYCLE*0.8)
        #(`CYCLE*0.2)
        WEN = 1'b0; RW = 3'd7; RX = 3'd0; RY = 3'd7;
        Ctrl = 4'b0011; Sel = 1'b1; DataIn = 8'd0;
        #(`CYCLE*0.3)
        if( busY==C ) $display( "    .... passed." );
        else begin 
            err_count = err_count+1;
            $display( "    .... failed, design(%b) != expected(%b)", busY, C );
        end
        $display( "Calculation restuls: %2d * %2d = %4d", A, B, busY );
        #(`HCYCLE)
        
        
        // show total results
        if( err_count==0 ) begin
            $display("****************************        /|__/|");
            $display("**                        **      / O,O  |");
            $display("**   Congratulations !!   **    /_____   |");
            $display("** All Patterns Passed!!  **   /^ ^ ^ \\  |");
            $display("**                        **  |^ ^ ^ ^ |w|");
            $display("****************************   \\m___m__|_|");
        end
        else begin
            $display("**************************** ");
            $display("           Failed ...        ");
            $display("     Total %2d Errors ...     ", err_count );
            $display("**************************** ");
        end
        
        // finish tb
        #(`CYCLE) $finish;
    end
    initial begin
    $dumpfile("simple.vcd");
    $dumpvars;
    end
endmodule

2HW/3-SimpleCalculator/simple.vcd
$date
    Apr 12, 2018  01:51:00
$end
$version
    TOOL:	ncsim	10.20-s114
$end
$timescale
    10 ps
$end

$scope module simple_calculator_tb $end
$var reg       1 !    Clk  $end
$var reg       1 "    WEN  $end
$var reg       3 #    RW [2:0] $end
$var reg       3 $    RX [2:0] $end
$var reg       3 %    RY [2:0] $end
$var reg       8 &    DataIn [7:0] $end
$var reg       1 '    Sel  $end
$var reg       4 (    Ctrl [3:0] $end
$var wire      8 )    busY [7:0] $end
$var wire      1 *    Carry  $end
$var parameter  8 +    A  $end
$var parameter  8 ,    B  $end
$var parameter  8 -    maskB0  $end
$var parameter  8 .    maskB1  $end
$var parameter  8 /    maskB2  $end
$var parameter  8 0    maskB3  $end
$var parameter  8 1    sum0  $end
$var parameter  8 2    sum1  $end
$var parameter  8 3    sum2  $end
$var parameter  8 4    C  $end
$var integer  32 5    err_count  $end

$scope module u_calc $end
$var wire      1 6    Clk  $end
$var wire      1 7    WEN  $end
$var wire      3 8    RW [2:0] $end
$var wire      3 9    RX [2:0] $end
$var wire      3 :    RY [2:0] $end
$var wire      8 ;    DataIn [7:0] $end
$var wire      1 <    Sel  $end
$var wire      4 =    Ctrl [3:0] $end
$var wire      8 )    busY [7:0] $end
$var wire      1 *    Carry  $end
$var reg       8 >    x [7:0] $end
$var reg       8 ?    y [7:0] $end
$var wire      8 @    busX [7:0] $end
$var wire      8 A    out [7:0] $end
$var wire      1 B    carry  $end

$scope module r $end
$var wire      1 6    Clk  $end
$var wire      1 7    WEN  $end
$var wire      3 8    RW [2:0] $end
$var wire      3 9    RX [2:0] $end
$var wire      3 :    RY [2:0] $end
$var wire      8 A    busW [7:0] $end
$var reg       8 C    busX [7:0] $end
$var reg       8 D    busY [7:0] $end
$var reg       8 E    r0_w [7:0] $end
$var reg       8 F    r1_w [7:0] $end
$var reg       8 G    r2_w [7:0] $end
$var reg       8 H    r3_w [7:0] $end
$var reg       8 I    r4_w [7:0] $end
$var reg       8 J    r5_w [7:0] $end
$var reg       8 K    r6_w [7:0] $end
$var reg       8 L    r7_w [7:0] $end
$var reg       8 M    r0_r [7:0] $end
$var reg       8 N    r1_r [7:0] $end
$var reg       8 O    r2_r [7:0] $end
$var reg       8 P    r3_r [7:0] $end
$var reg       8 Q    r4_r [7:0] $end
$var reg       8 R    r5_r [7:0] $end
$var reg       8 S    r6_r [7:0] $end
$var reg       8 T    r7_r [7:0] $end
$upscope $end


$scope module a $end
$var wire      4 =    ctrl [3:0] $end
$var wire      8 U    x [7:0] $end
$var wire      8 V    y [7:0] $end
$var reg       1 W    carry  $end
$var reg       8 X    out [7:0] $end
$var reg       1 Y    carry_add  $end
$var reg       1 Z    carry_sub  $end
$upscope $end

$upscope $end

$upscope $end

$enddefinitions $end
$dumpvars
b10011100 4
b110100 3
b0 2
b0 1
b11111111 0
b11111111 /
b0 .
b0 -
b1100 ,
b1101 +
1!
x"
bx #
bx $
bx %
bx &
x'
bx (
bx )
z*
b0 5
16
x7
bx 8
bx 9
bx :
bx ;
x<
bx =
bx >
bx ?
bx @
bx A
xB
bx C
bx D
bx E
bx F
bx G
bx H
bx I
bx J
bx K
bx L
b0 M
bx N
bx O
bx P
bx Q
bx R
bx S
bx T
bx U
bx V
xW
bx X
xY
xZ
$end
#200
1"
b1 #
b0 $
b0 %
b0 (
0'
b1101 &
b1101 ;
0<
b0 =
b0 :
b0 9
b1 8
17
b1101 >
b0 C
b0 D
b0 )
b0 @
b1101 U
b0 ?
b0 V
b1101 X
0W
0B
b1101 A
b1101 F
#500
0!
06
#1000
1!
16
b1101 N
#1200
0"
b1 %
b11 (
b0 &
b0 ;
b11 =
b1 :
07
b0 >
b1101 D
b1101 )
b0 U
b1101 ?
b0 X
b0 A
b1101 V
b0 F
b1101 X
b1101 A
b1101 F
#1500
0!
06
#2000
1!
16
#2200
1"
b10 #
b0 %
b0 (
b1100 &
b1100 ;
b0 =
b0 :
b10 8
17
b1100 >
b1101 G
b0 D
b0 )
b1100 U
b0 ?
b11001 X
b11001 A
b0 V
b11001 G
b1100 X
b1100 A
b1100 G
#2500
0!
06
#3000
1!
16
b1100 O
#3200
0"
b1 #
b10 %
b11 (
b0 &
b0 ;
b11 =
b10 :
b1 8
07
b0 >
b1100 F
b1100 D
b1100 )
b0 U
b1100 ?
b0 X
b0 A
b1100 V
b0 F
b1100 X
b1100 A
b1100 F
#3500
0!
06
#4000
1!
16
#4200
1"
b11 #
b10 (
b1 &
b1 ;
b10 =
b11 8
17
b1 >
b0 X
b1100 H
b0 A
b1 U
b0 H
#4500
0!
06
#5000
1!
16
b0 P
#5200
b11 %
b1 (
1'
b0 &
b0 ;
1<
b1 =
b11 :
b0 >
b11110101 X
1W
b0 D
b0 )
1B
b11110101 A
b0 U
b0 ?
b11110101 H
b11110100 X
b11110100 A
b0 V
b11110100 H
b0 X
0W
0B
b0 A
b0 H
#5500
0!
06
#6000
1!
16
#6200
0"
b11 (
b11 =
07
#6500
0!
06
#7000
1!
16
#7200
1"
b10 #
b10 $
b10 %
b1001 (
b1001 =
b10 :
b10 9
b10 8
17
b0 G
b1100 C
b1100 D
b1100 )
b1100 @
b1100 >
b1100 ?
b1100 V
b1100 U
b110 X
b110 A
b110 G
#7500
0!
06
#8000
1!
16
b110 O
b110 C
b110 D
b110 )
b110 @
b110 >
b110 ?
b110 V
b110 U
b11 X
b11 A
b11 G
#8200
b100 #
b0 $
b10 (
0'
b1 &
b1 ;
0<
b10 =
b0 9
b100 8
b1 >
b110 X
b11 I
b0 C
b0 @
b110 A
b1 U
b110 I
b0 X
b0 A
b0 I
#8500
0!
06
#9000
1!
16
b0 Q
#9200
b100 %
b1 (
1'
b0 &
b0 ;
1<
b1 =
b100 :
b0 >
b11111011 X
1W
b0 D
b0 )
1B
b11111011 A
b0 U
b0 ?
b11111011 I
b11111010 X
b11111010 A
b0 V
b11111010 I
b0 X
0W
0B
b0 A
b0 I
#9500
0!
06
#10000
1!
16
#10200
0"
b11 (
b11 =
07
#10500
0!
06
#11000
1!
16
#11200
1"
b10 #
b10 $
b10 %
b1001 (
b1001 =
b10 :
b10 9
b10 8
17
b0 G
b110 C
b110 D
b110 )
b110 @
b110 >
b110 ?
b110 V
b110 U
b11 X
b11 A
b11 G
#11500
0!
06
#12000
1!
16
b11 O
b11 C
b11 D
b11 )
b11 @
b11 >
b11 ?
b11 V
b11 U
b1 X
b1 A
b1 G
#12200
b101 #
b0 $
b10 (
0'
b1 &
b1 ;
0<
b10 =
b0 9
b101 8
b1 >
b11 X
b1 J
b0 C
b0 @
b11 A
b1 U
b11 J
b1 X
b1 A
b1 J
#12500
0!
06
#13000
1!
16
b1 R
#13200
b101 %
b1 (
1'
b0 &
b0 ;
1<
b1 =
b101 :
b0 >
b11111110 X
1W
b1 D
b1 )
1B
b11111110 A
b0 U
b1 ?
b11111110 J
b11111101 X
b11111101 A
b1 V
b11111101 J
b11111111 X
b11111111 A
b11111111 J
#13500
0!
06
#14000
1!
16
b11111111 R
b11111111 D
b11111111 )
b11111111 ?
b11111111 V
b1 X
b1 A
b1 J
#14200
0"
b11 (
b11 =
07
b11111111 X
0W
0B
b11111111 A
b11111111 J
#14500
0!
06
#15000
1!
16
#15200
1"
b10 #
b10 $
b10 %
b1001 (
b1001 =
b10 :
b10 9
b10 8
17
b0 X
b11111111 G
b11 C
b11 D
b11 )
b11 @
b0 A
b11 >
b11 ?
b0 G
b11 V
b11 U
b1 X
b1 A
b1 G
#15500
0!
06
#16000
1!
16
b1 O
b1 C
b1 D
b1 )
b1 @
b1 >
b1 ?
b1 V
b1 U
b0 X
b0 A
b0 G
#16200
b110 #
b0 $
b10 (
0'
b1 &
b1 ;
0<
b10 =
b0 9
b110 8
b1 X
b0 K
b0 C
b0 @
b1 A
b1 K
#16500
0!
06
#17000
1!
16
b1 S
#17200
b110 %
b1 (
1'
b0 &
b0 ;
1<
b1 =
b110 :
b0 >
b0 X
b0 A
b0 U
b0 K
b11111111 X
1W
1B
b11111111 A
b11111111 K
#17500
0!
06
#18000
1!
16
b11111111 S
b11111111 D
b11111111 )
b11111111 ?
b11111111 V
b1 X
b1 A
b1 K
#18200
0"
b11 (
b11 =
07
b11111111 X
0W
0B
b11111111 A
b11111111 K
#18500
0!
06
#19000
1!
16
#19200
1"
b11 #
b1 $
b11 %
b10 (
b10 =
b11 :
b1 9
b11 8
17
b0 X
b11111111 H
b1101 C
b0 D
b0 )
b1101 @
b0 A
b1101 >
b0 ?
b0 H
b0 V
b1101 U
#19500
0!
06
#20000
1!
16
#20200
b111 #
b0 $
b0 (
b0 =
b0 9
b111 8
b1101 X
b0 L
b0 C
b0 @
b1101 A
b0 >
b1101 L
b0 U
b0 X
b0 A
b0 L
#20500
0!
06
#21000
1!
16
b0 T
#21200
0"
b111 %
b11 (
b11 =
b111 :
07
#21500
0!
06
#22000
1!
16
#22200
1"
b100 #
b1 $
b100 %
b10 (
b10 =
b100 :
b1 9
b100 8
17
b1101 C
b1101 @
b1101 >
b1101 U
#22500
0!
06
#23000
1!
16
#23200
b0 $
b111 (
0'
b1 &
b1 ;
0<
b111 =
b0 9
b1 >
b0 C
b0 @
b1 U
#23500
0!
06
#24000
1!
16
#24200
b111 #
b111 $
b0 (
1'
b0 &
b0 ;
1<
b0 =
b111 9
b111 8
b0 >
b1 X
b1 A
b0 U
b1 L
b0 X
b0 A
b0 L
#24500
0!
06
#25000
1!
16
#25200
0"
b0 $
b111 %
b11 (
b11 =
b111 :
b0 9
07
#25500
0!
06
#26000
1!
16
#26200
1"
b101 #
b1 $
b101 %
b10 (
b10 =
b101 :
b1 9
b101 8
17
b0 J
b1101 C
b11111111 D
b11111111 )
b1101 @
b1101 >
b11111111 ?
b11111111 V
b1101 U
b1101 X
b1101 A
b1101 J
#26500
0!
06
#27000
1!
16
b1101 R
b1101 D
b1101 )
b1101 ?
b1101 V
#27200
b0 $
b111 (
0'
b10 &
b10 ;
0<
b111 =
b0 9
b10 >
b10100000 X
b0 C
b0 @
b10100000 A
b10 U
b10100000 J
b110100 X
b110100 A
b110100 J
#27500
0!
06
#28000
1!
16
b110100 R
b110100 D
b110100 )
b110100 ?
b110100 V
b11010000 X
b11010000 A
b11010000 J
#28200
b111 #
b111 $
b0 (
1'
b0 &
b0 ;
1<
b0 =
b111 9
b111 8
b0 >
b110110 X
b11010000 L
b110110 A
b0 U
b110110 L
b110100 X
b110100 A
b110100 L
#28500
0!
06
#29000
1!
16
b110100 T
b110100 C
b110100 @
b110100 >
b110100 U
b1101000 X
b1101000 A
b1101000 L
#29200
0"
b0 $
b111 %
b11 (
b11 =
b111 :
b0 9
07
b110100 X
b0 C
b0 @
b110100 A
b0 >
b110100 L
b0 U
#29500
0!
06
#30000
1!
16
#30200
1"
b110 #
b1 $
b110 %
b10 (
b10 =
b110 :
b1 9
b110 8
17
b0 X
b110100 K
b1101 C
b11111111 D
b11111111 )
b1101 @
b0 A
b1101 >
b11111111 ?
b0 K
b11111111 V
b1101 U
b1101 X
b1101 A
b1101 K
#30500
0!
06
#31000
1!
16
b1101 S
b1101 D
b1101 )
b1101 ?
b1101 V
#31200
b0 $
b111 (
0'
b11 &
b11 ;
0<
b111 =
b0 9
b11 >
b10100000 X
b0 C
b0 @
b10100000 A
b11 U
b10100000 K
b1101000 X
b1101000 A
b1101000 K
#31500
0!
06
#32000
1!
16
b1101000 S
b1101000 D
b1101000 )
b1101000 ?
b1101000 V
b1000000 X
b1000000 A
b1000000 K
#32200
b111 #
b111 $
b0 (
1'
b0 &
b0 ;
1<
b0 =
b111 9
b111 8
b0 >
b1101011 X
b1000000 L
b110100 C
b110100 @
b1101011 A
b0 U
b110100 >
b1101011 L
b1101000 X
b1101000 A
b110100 U
b1101000 L
b10011100 X
b10011100 A
b10011100 L
#32500
0!
06
#33000
1!
16
b10011100 T
b10011100 C
b10011100 @
b10011100 >
b10011100 U
b100 X
b100 A
b100 L
#33200
0"
b0 $
b111 %
b11 (
b11 =
b111 :
b0 9
07
b11111100 X
b0 C
b10011100 D
b10011100 )
b0 @
b11111100 A
b0 >
b10011100 ?
b11111100 L
b10011100 V
b0 U
b10011100 X
b10011100 A
b10011100 L
